omniart_eye_generator/__init__.py
omniart_eye_generator/eye_generator.py
omniart_eye_generator/generator.py
omniart_eye_generator/generator_model_state.pth
omniart_eye_generator-0.1.dist-info/METADATA
omniart_eye_generator-0.1.dist-info/WHEEL
omniart_eye_generator-0.1.dist-info/top_level.txt
omniart_eye_generator-0.1.dist-info/RECORD
