Metadata-Version: 2.1
Name: omniart-eye-generator
Version: 0.1
Summary: A cDCGAN that can generate eyes
Home-page: http://github.com/rogierknoester/omniart_eye_generator
Author: Rogier Knoester
Author-email: knoesterrogier+omniart@gmail.com
License: MIT
Platform: UNKNOWN
